unsiloed_sdk/__init__.py
unsiloed_sdk/client.py
unsiloed_sdk/exceptions.py
unsiloed_sdk/models.py
unsiloed_sdk/sync_client.py
unsiloed_sdk-0.1.4.dist-info/licenses/LICENSE
unsiloed_sdk-0.1.4.dist-info/METADATA
unsiloed_sdk-0.1.4.dist-info/WHEEL
unsiloed_sdk-0.1.4.dist-info/top_level.txt
unsiloed_sdk-0.1.4.dist-info/RECORD
