Metadata-Version: 2.4
Name: unsiloed-sdk
Version: 0.1.4
Summary: Python SDK for Unsiloed Vision API - Parse, Extract, Classify, and Split documents
Author-email: Unsiloed <support@unsiloed.com>
License: MIT
Project-URL: Homepage, https://unsiloed.ai
Project-URL: Documentation, https://docs.unsiloed.ai
Project-URL: Repository, https://github.com/unsiloed/unsiloed-sdk-python
Project-URL: Bug Tracker, https://github.com/unsiloed/unsiloed-sdk-python/issues
Keywords: unsiloed,document-processing,ocr,pdf,extraction,classification
Classifier: Development Status :: 4 - Beta
Classifier: Intended Audience :: Developers
Classifier: License :: OSI Approved :: MIT License
Classifier: Programming Language :: Python :: 3
Classifier: Programming Language :: Python :: 3.8
Classifier: Programming Language :: Python :: 3.9
Classifier: Programming Language :: Python :: 3.10
Classifier: Programming Language :: Python :: 3.11
Classifier: Programming Language :: Python :: 3.12
Classifier: Topic :: Software Development :: Libraries :: Python Modules
Requires-Python: >=3.8
License-File: LICENSE
Requires-Dist: httpx>=0.24.0
Provides-Extra: dev
Requires-Dist: pytest>=7.0.0; extra == "dev"
Requires-Dist: pytest-asyncio>=0.21.0; extra == "dev"
Requires-Dist: black>=23.0.0; extra == "dev"
Requires-Dist: isort>=5.12.0; extra == "dev"
Requires-Dist: mypy>=1.0.0; extra == "dev"
Dynamic: license-file
Dynamic: requires-python
